hedgehog/__init__.py
hedgehog/client/__init__.py
hedgehog/client/async_client.py
hedgehog/client/async_handlers.py
hedgehog/client/shutdown_handler.py
hedgehog/client/sync_client.py
hedgehog/client/test_utils.py
hedgehog_client-0.9.1.dist-info/LICENSE
hedgehog_client-0.9.1.dist-info/METADATA
hedgehog_client-0.9.1.dist-info/WHEEL
hedgehog_client-0.9.1.dist-info/entry_points.txt
hedgehog_client-0.9.1.dist-info/top_level.txt
hedgehog_client-0.9.1.dist-info/RECORD
